[
    {
        "Code":  "1444",
        "Name":  "力麗",
        "Market":  "上市",
        "Close":  "9.95",
        "Reason":  "最近六個營業日累積收盤價漲幅達37.63%﹝第一款﹞。且07月03日之成交量為最近六十個營業日日平均成交量之5.36倍﹝第三款﹞。",
        "Calculations":  [
                             {
                                 "Rule":  "6日累積漲跌幅 (標準 32%)",
                                 "BasePrice":  7.4099998474121094,
                                 "TargetUpPrice":  9.78,
                                 "TargetUpChange":  -1.71,
                                 "TargetDownPrice":  5.03,
                                 "TargetDownChange":  -49.45,
                                 "IsPrimary":  true
                             },
                             {
                                 "Rule":  "6日累積漲跌幅 (今日公告值 37.63%)",
                                 "BasePrice":  7.4099998474121094,
                                 "TargetUpPrice":  10.2,
                                 "TargetUpChange":  2.51,
                                 "TargetDownPrice":  4.62,
                                 "TargetDownChange":  -53.57,
                                 "IsPrimary":  false
                             },
                             {
                                 "Rule":  "30日累積漲跌幅 (100%)",
                                 "BasePrice":  5.9499998092651367,
                                 "TargetUpPrice":  11.9,
                                 "TargetUpChange":  19.6,
                                 "TargetDownPrice":  null,
                                 "TargetDownChange":  null,
                                 "IsPrimary":  false
                             },
                             {
                                 "Rule":  "60日累積漲跌幅 (130%)",
                                 "BasePrice":  6.21999979019165,
                                 "TargetUpPrice":  14.35,
                                 "TargetUpChange":  44.22,
                                 "TargetDownPrice":  null,
                                 "TargetDownChange":  null,
                                 "IsPrimary":  false
                             },
                             {
                                 "Rule":  "90日累積漲跌幅 (160%)",
                                 "BasePrice":  6.3499999046325684,
                                 "TargetUpPrice":  16.55,
                                 "TargetUpChange":  66.33,
                                 "TargetDownPrice":  null,
                                 "TargetDownChange":  null,
                                 "IsPrimary":  false
                             }
                         ],
        "VolumeCalculations":  [
                                   {
                                       "Rule":  "60日日平均成交量放大倍數 (5.36 倍)",
                                       "Baseline":  3647867.42,
                                       "TriggerVolume":  19552569
                                   }
                               ]
    },
    {
        "Code":  "1515",
        "Name":  "力山",
        "Market":  "上市",
        "Close":  "42.00",
        "Reason":  "最近六個營業日累積收盤價漲幅達35.96%﹝第一款﹞。且07月03日之成交量為最近六十個營業日日平均成交量之7.98倍﹝第三款﹞。",
        "Calculations":  [
                             {
                                 "Rule":  "6日累積漲跌幅 (標準 32%)",
                                 "BasePrice":  30.5,
                                 "TargetUpPrice":  40.3,
                                 "TargetUpChange":  -4.05,
                                 "TargetDownPrice":  20.7,
                                 "TargetDownChange":  -50.71,
                                 "IsPrimary":  true
                             },
                             {
                                 "Rule":  "6日累積漲跌幅 (今日公告值 35.96%)",
                                 "BasePrice":  30.5,
                                 "TargetUpPrice":  41.5,
                                 "TargetUpChange":  -1.19,
                                 "TargetDownPrice":  19.5,
                                 "TargetDownChange":  -53.57,
                                 "IsPrimary":  false
                             },
                             {
                                 "Rule":  "30日累積漲跌幅 (100%)",
                                 "BasePrice":  22.649999618530273,
                                 "TargetUpPrice":  45.3,
                                 "TargetUpChange":  7.86,
                                 "TargetDownPrice":  null,
                                 "TargetDownChange":  null,
                                 "IsPrimary":  false
                             },
                             {
                                 "Rule":  "60日累積漲跌幅 (130%)",
                                 "BasePrice":  23.799999237060547,
                                 "TargetUpPrice":  54.8,
                                 "TargetUpChange":  30.48,
                                 "TargetDownPrice":  null,
                                 "TargetDownChange":  null,
                                 "IsPrimary":  false
                             },
                             {
                                 "Rule":  "90日累積漲跌幅 (160%)",
                                 "BasePrice":  26.75,
                                 "TargetUpPrice":  69.6,
                                 "TargetUpChange":  65.71,
                                 "TargetDownPrice":  null,
                                 "TargetDownChange":  null,
                                 "IsPrimary":  false
                             }
                         ],
        "VolumeCalculations":  [
                                   {
                                       "Rule":  "60日日平均成交量放大倍數 (7.98 倍)",
                                       "Baseline":  1652065.02,
                                       "TriggerVolume":  13183479
                                   }
                               ]
    },
    {
        "Code":  "1718",
        "Name":  "中纖",
        "Market":  "上市",
        "Close":  "14.95",
        "Reason":  "最近六個營業日累積收盤價漲幅達41.29%﹝第一款﹞。且07月03日之成交量為最近六十個營業日日平均成交量之5.83倍﹝第三款﹞。且07月03日凱基證券商買進之比率為40.35%﹝第五款﹞。最近三十個營業日起迄兩個營業日之收盤價漲幅達131.42% ﹝第二款﹞。",
        "Calculations":  [
                             {
                                 "Rule":  "6日累積漲跌幅 (標準 32%)",
                                 "BasePrice":  11.149999618530272,
                                 "TargetUpPrice":  14.75,
                                 "TargetUpChange":  -1.34,
                                 "TargetDownPrice":  7.57,
                                 "TargetDownChange":  -49.36,
                                 "IsPrimary":  true
                             },
                             {
                                 "Rule":  "6日累積漲跌幅 (今日公告值 131.42%)",
                                 "BasePrice":  11.149999618530272,
                                 "TargetUpPrice":  25.8,
                                 "TargetUpChange":  72.58,
                                 "TargetDownPrice":  -3.5,
                                 "TargetDownChange":  -123.41,
                                 "IsPrimary":  false
                             },
                             {
                                 "Rule":  "30日累積漲跌幅 (131.42%)",
                                 "BasePrice":  6.4600000381469727,
                                 "TargetUpPrice":  14.95,
                                 "TargetUpChange":  0,
                                 "TargetDownPrice":  null,
                                 "TargetDownChange":  null,
                                 "IsPrimary":  true
                             },
                             {
                                 "Rule":  "60日累積漲跌幅 (131.42%)",
                                 "BasePrice":  7.3299999237060547,
                                 "TargetUpPrice":  17,
                                 "TargetUpChange":  13.71,
                                 "TargetDownPrice":  null,
                                 "TargetDownChange":  null,
                                 "IsPrimary":  true
                             },
                             {
                                 "Rule":  "90日累積漲跌幅 (160%)",
                                 "BasePrice":  7.0799999237060547,
                                 "TargetUpPrice":  18.45,
                                 "TargetUpChange":  23.41,
                                 "TargetDownPrice":  null,
                                 "TargetDownChange":  null,
                                 "IsPrimary":  false
                             }
                         ],
        "VolumeCalculations":  [
                                   {
                                       "Rule":  "60日日平均成交量放大倍數 (5.83 倍)",
                                       "Baseline":  25422830.72,
                                       "TriggerVolume":  148215103
                                   }
                               ]
    },
    {
        "Code":  "2484",
        "Name":  "希華",
        "Market":  "上市",
        "Close":  "96.40",
        "Reason":  "最近六個營業日累積收盤價漲幅達34.61%﹝第一款﹞。且07月03日之週轉率為73.86%﹝第四款﹞。最近六十個營業日起迄兩個營業日之收盤價漲幅達217.10% 。最近九十個營業日起迄兩個營業日之收盤價漲幅達240.63% ﹝第二款﹞。",
        "Calculations":  [
                             {
                                 "Rule":  "6日累積漲跌幅 (標準 32%)",
                                 "BasePrice":  76.800003051757813,
                                 "TargetUpPrice":  101.5,
                                 "TargetUpChange":  5.29,
                                 "TargetDownPrice":  52.2,
                                 "TargetDownChange":  -45.85,
                                 "IsPrimary":  true
                             },
                             {
                                 "Rule":  "6日累積漲跌幅 (今日公告值 240.63%)",
                                 "BasePrice":  76.800003051757813,
                                 "TargetUpPrice":  262,
                                 "TargetUpChange":  171.78,
                                 "TargetDownPrice":  -108,
                                 "TargetDownChange":  -212.03,
                                 "IsPrimary":  false
                             },
                             {
                                 "Rule":  "30日累積漲跌幅 (100%)",
                                 "BasePrice":  49.299999237060547,
                                 "TargetUpPrice":  98.6,
                                 "TargetUpChange":  2.28,
                                 "TargetDownPrice":  null,
                                 "TargetDownChange":  null,
                                 "IsPrimary":  false
                             },
                             {
                                 "Rule":  "60日累積漲跌幅 (240.63%)",
                                 "BasePrice":  30.399999618530273,
                                 "TargetUpPrice":  104,
                                 "TargetUpChange":  7.88,
                                 "TargetDownPrice":  null,
                                 "TargetDownChange":  null,
                                 "IsPrimary":  true
                             },
                             {
                                 "Rule":  "90日累積漲跌幅 (240.63%)",
                                 "BasePrice":  28.299999237060547,
                                 "TargetUpPrice":  96.4,
                                 "TargetUpChange":  0,
                                 "TargetDownPrice":  null,
                                 "TargetDownChange":  null,
                                 "IsPrimary":  true
                             }
                         ],
        "VolumeCalculations":  [
                                   {
                                       "Rule":  "60日日平均成交量放大倍數 (5 倍)",
                                       "Baseline":  29702645.72,
                                       "TriggerVolume":  148513229
                                   },
                                   {
                                       "Rule":  "當日週轉率達 10.0% 門檻",
                                       "Baseline":  158931433.79366368,
                                       "TriggerVolume":  15893143
                                   },
                                   {
                                       "Rule":  "6日累積週轉率達 50.0% 門檻 (明日需達 -142.94%)",
                                       "Baseline":  158931433.79366368,
                                       "TriggerVolume":  0
                                   }
                               ]
    },
    {
        "Code":  "3016",
        "Name":  "嘉晶",
        "Market":  "上市",
        "Close":  "135.50",
        "Reason":  "最近六十個營業日起迄兩個營業日之收盤價漲幅達150.90% ﹝第二款﹞。",
        "Calculations":  [
                             {
                                 "Rule":  "6日累積漲跌幅 (標準 32%)",
                                 "BasePrice":  124.5,
                                 "TargetUpPrice":  164.5,
                                 "TargetUpChange":  21.4,
                                 "TargetDownPrice":  84.6,
                                 "TargetDownChange":  -37.56,
                                 "IsPrimary":  true
                             },
                             {
                                 "Rule":  "30日累積漲跌幅 (100%)",
                                 "BasePrice":  121,
                                 "TargetUpPrice":  242,
                                 "TargetUpChange":  78.6,
                                 "TargetDownPrice":  null,
                                 "TargetDownChange":  null,
                                 "IsPrimary":  false
                             },
                             {
                                 "Rule":  "60日累積漲跌幅 (150.9%)",
                                 "BasePrice":  54.200000762939453,
                                 "TargetUpPrice":  136,
                                 "TargetUpChange":  0.37,
                                 "TargetDownPrice":  null,
                                 "TargetDownChange":  null,
                                 "IsPrimary":  true
                             },
                             {
                                 "Rule":  "90日累積漲跌幅 (160%)",
                                 "BasePrice":  58.900001525878906,
                                 "TargetUpPrice":  153.5,
                                 "TargetUpChange":  13.28,
                                 "TargetDownPrice":  null,
                                 "TargetDownChange":  null,
                                 "IsPrimary":  false
                             }
                         ],
        "VolumeCalculations":  [
                                   {
                                       "Rule":  "60日日平均成交量放大倍數 (5 倍)",
                                       "Baseline":  8740662.42,
                                       "TriggerVolume":  43703312
                                   }
                               ]
    },
    {
        "Code":  "3023",
        "Name":  "信邦",
        "Market":  "上市",
        "Close":  "336.50",
        "Reason":  "07月02日之最近六個營業日之借券賣出成交量占最近六個營業日總成交量比率18.11%，且07月02日借券賣出成交量較最近六十個營業日之日平均借券賣出成交量放大為5.82倍\u003cfont color=\u0027#FF0000\u0027\u003e﹝第十二款﹞\u003c/font\u003e。",
        "Calculations":  [
                             {
                                 "Rule":  "6日累積漲跌幅 (標準 32%)",
                                 "BasePrice":  306.5,
                                 "TargetUpPrice":  405,
                                 "TargetUpChange":  20.36,
                                 "TargetDownPrice":  208,
                                 "TargetDownChange":  -38.19,
                                 "IsPrimary":  true
                             },
                             {
                                 "Rule":  "30日累積漲跌幅 (100%)",
                                 "BasePrice":  314.5,
                                 "TargetUpPrice":  629,
                                 "TargetUpChange":  86.92,
                                 "TargetDownPrice":  null,
                                 "TargetDownChange":  null,
                                 "IsPrimary":  false
                             },
                             {
                                 "Rule":  "60日累積漲跌幅 (130%)",
                                 "BasePrice":  272,
                                 "TargetUpPrice":  626,
                                 "TargetUpChange":  86.03,
                                 "TargetDownPrice":  null,
                                 "TargetDownChange":  null,
                                 "IsPrimary":  false
                             },
                             {
                                 "Rule":  "90日累積漲跌幅 (160%)",
                                 "BasePrice":  239.5,
                                 "TargetUpPrice":  623,
                                 "TargetUpChange":  85.14,
                                 "TargetDownPrice":  null,
                                 "TargetDownChange":  null,
                                 "IsPrimary":  false
                             }
                         ],
        "VolumeCalculations":  [
                                   {
                                       "Rule":  "60日日平均成交量放大倍數 (5 倍)",
                                       "Baseline":  2213849.58,
                                       "TriggerVolume":  11069248
                                   }
                               ]
    },
    {
        "Code":  "3042",
        "Name":  "晶技",
        "Market":  "上市",
        "Close":  "249.00",
        "Reason":  "最近六個營業日累積收盤價漲幅達30.13%。且六個營業日起迄兩個營業日收盤價價差達56.00 元﹝第一款﹞。且07月03日之週轉率為29.26%﹝第四款﹞。",
        "Calculations":  [
                             {
                                 "Rule":  "6日累積漲跌幅 (標準 32%)",
                                 "BasePrice":  193,
                                 "TargetUpPrice":  255,
                                 "TargetUpChange":  2.41,
                                 "TargetDownPrice":  131,
                                 "TargetDownChange":  -47.39,
                                 "IsPrimary":  true
                             },
                             {
                                 "Rule":  "6日累積漲跌幅 (今日公告值 30.13%)",
                                 "BasePrice":  193,
                                 "TargetUpPrice":  251.5,
                                 "TargetUpChange":  1,
                                 "TargetDownPrice":  134.5,
                                 "TargetDownChange":  -45.98,
                                 "IsPrimary":  false
                             },
                             {
                                 "Rule":  "6日收盤價差 (56 元) 且為最高/最低",
                                 "BasePrice":  193,
                                 "TargetUpPrice":  249,
                                 "TargetUpChange":  0,
                                 "TargetDownPrice":  137,
                                 "TargetDownChange":  -44.98,
                                 "IsPrimary":  true
                             },
                             {
                                 "Rule":  "30日累積漲跌幅 (100%)",
                                 "BasePrice":  176,
                                 "TargetUpPrice":  352,
                                 "TargetUpChange":  41.37,
                                 "TargetDownPrice":  null,
                                 "TargetDownChange":  null,
                                 "IsPrimary":  false
                             },
                             {
                                 "Rule":  "60日累積漲跌幅 (130%)",
                                 "BasePrice":  107.5,
                                 "TargetUpPrice":  247.5,
                                 "TargetUpChange":  -0.6,
                                 "TargetDownPrice":  null,
                                 "TargetDownChange":  null,
                                 "IsPrimary":  false
                             },
                             {
                                 "Rule":  "90日累積漲跌幅 (160%)",
                                 "BasePrice":  90.3000030517578,
                                 "TargetUpPrice":  235,
                                 "TargetUpChange":  -5.62,
                                 "TargetDownPrice":  null,
                                 "TargetDownChange":  null,
                                 "IsPrimary":  false
                             }
                         ],
        "VolumeCalculations":  [
                                   {
                                       "Rule":  "60日日平均成交量放大倍數 (5 倍)",
                                       "Baseline":  24954521.03,
                                       "TriggerVolume":  124772605
                                   },
                                   {
                                       "Rule":  "當日週轉率達 10.0% 門檻",
                                       "Baseline":  313788677.3752563,
                                       "TriggerVolume":  31378868
                                   },
                                   {
                                       "Rule":  "6日累積週轉率達 50.0% 門檻 (明日需達 -16.42%)",
                                       "Baseline":  313788677.3752563,
                                       "TriggerVolume":  0
                                   }
                               ]
    },
    {
        "Code":  "4904",
        "Name":  "遠傳",
        "Market":  "上市",
        "Close":  "105.00",
        "Reason":  "07月02日之最近六個營業日之借券賣出成交量占最近六個營業日總成交量比率20.36%，且07月02日借券賣出成交量較最近六十個營業日之日平均借券賣出成交量放大為6.64倍\u003cfont color=\u0027#FF0000\u0027\u003e﹝第十二款﹞\u003c/font\u003e。",
        "Calculations":  [
                             {
                                 "Rule":  "6日累積漲跌幅 (標準 32%)",
                                 "BasePrice":  107,
                                 "TargetUpPrice":  141.5,
                                 "TargetUpChange":  34.76,
                                 "TargetDownPrice":  72.7,
                                 "TargetDownChange":  -30.76,
                                 "IsPrimary":  true
                             },
                             {
                                 "Rule":  "30日累積漲跌幅 (100%)",
                                 "BasePrice":  95.5,
                                 "TargetUpPrice":  191,
                                 "TargetUpChange":  81.9,
                                 "TargetDownPrice":  null,
                                 "TargetDownChange":  null,
                                 "IsPrimary":  false
                             },
                             {
                                 "Rule":  "60日累積漲跌幅 (130%)",
                                 "BasePrice":  95.3000030517578,
                                 "TargetUpPrice":  219.5,
                                 "TargetUpChange":  109.05,
                                 "TargetDownPrice":  null,
                                 "TargetDownChange":  null,
                                 "IsPrimary":  false
                             },
                             {
                                 "Rule":  "90日累積漲跌幅 (160%)",
                                 "BasePrice":  94.8000030517578,
                                 "TargetUpPrice":  246.5,
                                 "TargetUpChange":  134.76,
                                 "TargetDownPrice":  null,
                                 "TargetDownChange":  null,
                                 "IsPrimary":  false
                             }
                         ],
        "VolumeCalculations":  [
                                   {
                                       "Rule":  "60日日平均成交量放大倍數 (5 倍)",
                                       "Baseline":  11451131.52,
                                       "TriggerVolume":  57255658
                                   }
                               ]
    },
    {
        "Code":  "6415",
        "Name":  "矽力*-KY",
        "Market":  "上市",
        "Close":  "673",
        "Reason":  "【已處置有價證券】處置期間: 115/06/24～115/07/07 。現正執行人工管制撮合及預收款券等處置措施。",
        "IsDisposed":  true,
        "DisposedPeriod":  "115/06/24～115/07/07",
        "Calculations":  [

                         ],
        "VolumeCalculations":  [

                               ]
    },
    {
        "Code":  "3147",
        "Name":  "大綜",
        "Market":  "上櫃",
        "Close":  "236.00",
        "Reason":  "【已處置有價證券】處置期間: 1150706~1150717 。現正執行人工管制撮合及預收款券等處置措施。",
        "IsDisposed":  true,
        "DisposedPeriod":  "1150706~1150717",
        "Calculations":  [

                         ],
        "VolumeCalculations":  [

                               ]
    },
    {
        "Code":  "5227",
        "Name":  "立凱-KY",
        "Market":  "上櫃",
        "Close":  "33.950000762939453",
        "Reason":  "【已處置有價證券】處置期間: 1150624~1150707 。現正執行人工管制撮合及預收款券等處置措施。",
        "IsDisposed":  true,
        "DisposedPeriod":  "1150624~1150707",
        "Calculations":  [

                         ],
        "VolumeCalculations":  [

                               ]
    },
    {
        "Code":  "4551",
        "Name":  "智伸科",
        "Market":  "上市",
        "Close":  "226",
        "Reason":  "【已處置有價證券】處置期間: 115/06/23～115/07/06 。現正執行人工管制撮合及預收款券等處置措施。",
        "IsDisposed":  true,
        "DisposedPeriod":  "115/06/23～115/07/06",
        "Calculations":  [

                         ],
        "VolumeCalculations":  [

                               ]
    },
    {
        "Code":  "61828",
        "Name":  "合晶八",
        "Market":  "上櫃",
        "Close":  "499.00",
        "Reason":  "【已處置有價證券】處置期間: 1150622~1150703 。現正執行人工管制撮合及預收款券等處置措施。",
        "IsDisposed":  true,
        "DisposedPeriod":  "1150622~1150703",
        "Calculations":  [

                         ],
        "VolumeCalculations":  [

                               ]
    },
    {
        "Code":  "80212",
        "Name":  "尖點二",
        "Market":  "上櫃",
        "Close":  "N/A",
        "Reason":  "【已處置有價證券】處置期間: 1150703~1150716 。現正執行人工管制撮合及預收款券等處置措施。",
        "IsDisposed":  true,
        "DisposedPeriod":  "1150703~1150716",
        "Calculations":  [

                         ],
        "VolumeCalculations":  [

                               ]
    },
    {
        "Code":  "8021",
        "Name":  "尖點",
        "Market":  "上市",
        "Close":  "544",
        "Reason":  "【已處置有價證券】處置期間: 115/07/03～115/07/16 。現正執行人工管制撮合及預收款券等處置措施。",
        "IsDisposed":  true,
        "DisposedPeriod":  "115/07/03～115/07/16",
        "Calculations":  [

                         ],
        "VolumeCalculations":  [

                               ]
    },
    {
        "Code":  "2305",
        "Name":  "全友",
        "Market":  "上市",
        "Close":  "37",
        "Reason":  "【已處置有價證券】處置期間: 115/06/24～115/07/07 。現正執行人工管制撮合及預收款券等處置措施。",
        "IsDisposed":  true,
        "DisposedPeriod":  "115/06/24～115/07/07",
        "Calculations":  [

                         ],
        "VolumeCalculations":  [

                               ]
    },
    {
        "Code":  "2483",
        "Name":  "百容",
        "Market":  "上市",
        "Close":  "67.10",
        "Reason":  "【已處置有價證券】處置期間: 115/06/30～115/07/13 。現正執行人工管制撮合及預收款券等處置措施。",
        "IsDisposed":  true,
        "DisposedPeriod":  "115/06/30～115/07/13",
        "Calculations":  [

                         ],
        "VolumeCalculations":  [

                               ]
    },
    {
        "Code":  "6243",
        "Name":  "迅杰",
        "Market":  "上市",
        "Close":  "43",
        "Reason":  "【已處置有價證券】處置期間: 115/06/29～115/07/10 。現正執行人工管制撮合及預收款券等處置措施。",
        "IsDisposed":  true,
        "DisposedPeriod":  "115/06/29～115/07/10",
        "Calculations":  [

                         ],
        "VolumeCalculations":  [

                               ]
    },
    {
        "Code":  "3189",
        "Name":  "景碩",
        "Market":  "上市",
        "Close":  "830",
        "Reason":  "【已處置有價證券】處置期間: 115/07/03～115/07/16 。現正執行人工管制撮合及預收款券等處置措施。",
        "IsDisposed":  true,
        "DisposedPeriod":  "115/07/03～115/07/16",
        "Calculations":  [

                         ],
        "VolumeCalculations":  [

                               ]
    },
    {
        "Code":  "707059",
        "Name":  "健亞永豐5B購01",
        "Market":  "上櫃",
        "Close":  "N/A",
        "Reason":  "【已處置有價證券】處置期間: 1150624~1150707 。現正執行人工管制撮合及預收款券等處置措施。",
        "IsDisposed":  true,
        "DisposedPeriod":  "1150624~1150707",
        "Calculations":  [

                         ],
        "VolumeCalculations":  [

                               ]
    },
    {
        "Code":  "4923",
        "Name":  "力士",
        "Market":  "上櫃",
        "Close":  "63.400001525878906",
        "Reason":  "【已處置有價證券】處置期間: 1150624~1150707 。現正執行人工管制撮合及預收款券等處置措施。",
        "IsDisposed":  true,
        "DisposedPeriod":  "1150624~1150707",
        "Calculations":  [

                         ],
        "VolumeCalculations":  [

                               ]
    },
    {
        "Code":  "6620",
        "Name":  "漢達",
        "Market":  "上櫃",
        "Close":  "99.9000015258789",
        "Reason":  "【已處置有價證券】處置期間: 1150626~1150709 。現正執行人工管制撮合及預收款券等處置措施。",
        "IsDisposed":  true,
        "DisposedPeriod":  "1150626~1150709",
        "Calculations":  [

                         ],
        "VolumeCalculations":  [

                               ]
    },
    {
        "Code":  "3441",
        "Name":  "聯一光",
        "Market":  "上櫃",
        "Close":  "89.0999984741211",
        "Reason":  "【已處置有價證券】處置期間: 1150622~1150707 。現正執行人工管制撮合及預收款券等處置措施。",
        "IsDisposed":  true,
        "DisposedPeriod":  "1150622~1150707",
        "Calculations":  [

                         ],
        "VolumeCalculations":  [

                               ]
    },
    {
        "Code":  "2243",
        "Name":  "宏旭-KY",
        "Market":  "上市",
        "Close":  "40.900001525878906",
        "Reason":  "【已處置有價證券】處置期間: 115/06/23～115/07/06 。現正執行人工管制撮合及預收款券等處置措施。",
        "IsDisposed":  true,
        "DisposedPeriod":  "115/06/23～115/07/06",
        "Calculations":  [

                         ],
        "VolumeCalculations":  [

                               ]
    },
    {
        "Code":  "059570",
        "Name":  "強茂凱基5B購03",
        "Market":  "上市",
        "Close":  "16.700000762939453",
        "Reason":  "【已處置有價證券】處置期間: 115/07/03～115/07/16 。現正執行人工管制撮合及預收款券等處置措施。",
        "IsDisposed":  true,
        "DisposedPeriod":  "115/07/03～115/07/16",
        "Calculations":  [

                         ],
        "VolumeCalculations":  [

                               ]
    },
    {
        "Code":  "6217",
        "Name":  "中探針",
        "Market":  "上櫃",
        "Close":  "269.00",
        "Reason":  "【已處置有價證券】處置期間: 1150706~1150717 。現正執行人工管制撮合及預收款券等處置措施。",
        "IsDisposed":  true,
        "DisposedPeriod":  "1150706~1150717",
        "Calculations":  [

                         ],
        "VolumeCalculations":  [

                               ]
    },
    {
        "Code":  "24552",
        "Name":  "全新二",
        "Market":  "上櫃",
        "Close":  "N/A",
        "Reason":  "【已處置有價證券】處置期間: 1150622~1150703 。現正執行人工管制撮合及預收款券等處置措施。",
        "IsDisposed":  true,
        "DisposedPeriod":  "1150622~1150703",
        "Calculations":  [

                         ],
        "VolumeCalculations":  [

                               ]
    },
    {
        "Code":  "61827",
        "Name":  "合晶七",
        "Market":  "上櫃",
        "Close":  "269.00",
        "Reason":  "【已處置有價證券】處置期間: 1150622~1150703 。現正執行人工管制撮合及預收款券等處置措施。",
        "IsDisposed":  true,
        "DisposedPeriod":  "1150622~1150703",
        "Calculations":  [

                         ],
        "VolumeCalculations":  [

                               ]
    },
    {
        "Code":  "3163",
        "Name":  "波若威",
        "Market":  "上櫃",
        "Close":  "903",
        "Reason":  "【已處置有價證券】處置期間: 1150622~1150703 。現正執行人工管制撮合及預收款券等處置措施。",
        "IsDisposed":  true,
        "DisposedPeriod":  "1150622~1150703",
        "Calculations":  [

                         ],
        "VolumeCalculations":  [

                               ]
    },
    {
        "Code":  "53211",
        "Name":  "美而快一",
        "Market":  "上櫃",
        "Close":  "N/A",
        "Reason":  "【已處置有價證券】處置期間: 1150629~1150710 。現正執行人工管制撮合及預收款券等處置措施。",
        "IsDisposed":  true,
        "DisposedPeriod":  "1150629~1150710",
        "Calculations":  [

                         ],
        "VolumeCalculations":  [

                               ]
    },
    {
        "Code":  "76101",
        "Name":  "聯友金屬一創",
        "Market":  "上櫃",
        "Close":  "227",
        "Reason":  "【已處置有價證券】處置期間: 1150624~1150707 。現正執行人工管制撮合及預收款券等處置措施。",
        "IsDisposed":  true,
        "DisposedPeriod":  "1150624~1150707",
        "Calculations":  [

                         ],
        "VolumeCalculations":  [

                               ]
    },
    {
        "Code":  "3090",
        "Name":  "日電貿",
        "Market":  "上市",
        "Close":  "335.5",
        "Reason":  "【已處置有價證券】處置期間: 115/06/23～115/07/08 。現正執行人工管制撮合及預收款券等處置措施。",
        "IsDisposed":  true,
        "DisposedPeriod":  "115/06/23～115/07/08",
        "Calculations":  [

                         ],
        "VolumeCalculations":  [

                               ]
    },
    {
        "Code":  "54642",
        "Name":  "霖宏二",
        "Market":  "上櫃",
        "Close":  "280",
        "Reason":  "【已處置有價證券】處置期間: 1150629~1150710 。現正執行人工管制撮合及預收款券等處置措施。",
        "IsDisposed":  true,
        "DisposedPeriod":  "1150629~1150710",
        "Calculations":  [

                         ],
        "VolumeCalculations":  [

                               ]
    },
    {
        "Code":  "2316",
        "Name":  "楠梓電",
        "Market":  "上市",
        "Close":  "226",
        "Reason":  "【已處置有價證券】處置期間: 115/06/25～115/07/08 。現正執行人工管制撮合及預收款券等處置措施。",
        "IsDisposed":  true,
        "DisposedPeriod":  "115/06/25～115/07/08",
        "Calculations":  [

                         ],
        "VolumeCalculations":  [

                               ]
    },
    {
        "Code":  "6715",
        "Name":  "嘉基",
        "Market":  "上市",
        "Close":  "518",
        "Reason":  "【已處置有價證券】處置期間: 115/06/25～115/07/08 。現正執行人工管制撮合及預收款券等處置措施。",
        "IsDisposed":  true,
        "DisposedPeriod":  "115/06/25～115/07/08",
        "Calculations":  [

                         ],
        "VolumeCalculations":  [

                               ]
    },
    {
        "Code":  "2233",
        "Name":  "宇隆",
        "Market":  "上市",
        "Close":  "193",
        "Reason":  "【已處置有價證券】處置期間: 115/06/30～115/07/13 。現正執行人工管制撮合及預收款券等處置措施。",
        "IsDisposed":  true,
        "DisposedPeriod":  "115/06/30～115/07/13",
        "Calculations":  [

                         ],
        "VolumeCalculations":  [

                               ]
    },
    {
        "Code":  "89964",
        "Name":  "高力四",
        "Market":  "上櫃",
        "Close":  "N/A",
        "Reason":  "【已處置有價證券】處置期間: 1150624~1150707 。現正執行人工管制撮合及預收款券等處置措施。",
        "IsDisposed":  true,
        "DisposedPeriod":  "1150624~1150707",
        "Calculations":  [

                         ],
        "VolumeCalculations":  [

                               ]
    },
    {
        "Code":  "8096",
        "Name":  "擎亞",
        "Market":  "上櫃",
        "Close":  "157.5",
        "Reason":  "【已處置有價證券】處置期間: 1150624~1150707 。現正執行人工管制撮合及預收款券等處置措施。",
        "IsDisposed":  true,
        "DisposedPeriod":  "1150624~1150707",
        "Calculations":  [

                         ],
        "VolumeCalculations":  [

                               ]
    },
    {
        "Code":  "2492",
        "Name":  "華新科",
        "Market":  "上市",
        "Close":  "617",
        "Reason":  "【已處置有價證券】處置期間: 115/06/24～115/07/07 。現正執行人工管制撮合及預收款券等處置措施。",
        "IsDisposed":  true,
        "DisposedPeriod":  "115/06/24～115/07/07",
        "Calculations":  [

                         ],
        "VolumeCalculations":  [

                               ]
    },
    {
        "Code":  "1303",
        "Name":  "南亞",
        "Market":  "上市",
        "Close":  "152.5",
        "Reason":  "【已處置有價證券】處置期間: 115/06/24～115/07/07 。現正執行人工管制撮合及預收款券等處置措施。",
        "IsDisposed":  true,
        "DisposedPeriod":  "115/06/24～115/07/07",
        "Calculations":  [

                         ],
        "VolumeCalculations":  [

                               ]
    },
    {
        "Code":  "5464",
        "Name":  "霖宏",
        "Market":  "上櫃",
        "Close":  "107.5",
        "Reason":  "【已處置有價證券】處置期間: 1150629~1150710 。現正執行人工管制撮合及預收款券等處置措施。",
        "IsDisposed":  true,
        "DisposedPeriod":  "1150629~1150710",
        "Calculations":  [

                         ],
        "VolumeCalculations":  [

                               ]
    },
    {
        "Code":  "8033",
        "Name":  "雷虎",
        "Market":  "上市",
        "Close":  "204.50",
        "Reason":  "【已處置有價證券】處置期間: 115/07/03～115/07/16 。現正執行人工管制撮合及預收款券等處置措施。",
        "IsDisposed":  true,
        "DisposedPeriod":  "115/07/03～115/07/16",
        "Calculations":  [

                         ],
        "VolumeCalculations":  [

                               ]
    },
    {
        "Code":  "3624",
        "Name":  "光頡",
        "Market":  "上櫃",
        "Close":  "176.5",
        "Reason":  "【已處置有價證券】處置期間: 1150624~1150709 。現正執行人工管制撮合及預收款券等處置措施。",
        "IsDisposed":  true,
        "DisposedPeriod":  "1150624~1150709",
        "Calculations":  [

                         ],
        "VolumeCalculations":  [

                               ]
    },
    {
        "Code":  "3230",
        "Name":  "錦明",
        "Market":  "上櫃",
        "Close":  "51.60",
        "Reason":  "【已處置有價證券】處置期間: 1150701~1150714 。現正執行人工管制撮合及預收款券等處置措施。",
        "IsDisposed":  true,
        "DisposedPeriod":  "1150701~1150714",
        "Calculations":  [

                         ],
        "VolumeCalculations":  [

                               ]
    },
    {
        "Code":  "6226",
        "Name":  "光鼎",
        "Market":  "上市",
        "Close":  "24.00",
        "Reason":  "【已處置有價證券】處置期間: 115/06/30～115/07/13 。現正執行人工管制撮合及預收款券等處置措施。",
        "IsDisposed":  true,
        "DisposedPeriod":  "115/06/30～115/07/13",
        "Calculations":  [

                         ],
        "VolumeCalculations":  [

                               ]
    },
    {
        "Code":  "2342",
        "Name":  "茂矽",
        "Market":  "上市",
        "Close":  "58.599998474121094",
        "Reason":  "【已處置有價證券】處置期間: 115/06/24～115/07/07 。現正執行人工管制撮合及預收款券等處置措施。",
        "IsDisposed":  true,
        "DisposedPeriod":  "115/06/24～115/07/07",
        "Calculations":  [

                         ],
        "VolumeCalculations":  [

                               ]
    },
    {
        "Code":  "22331",
        "Name":  "宇隆一",
        "Market":  "上櫃",
        "Close":  "N/A",
        "Reason":  "【已處置有價證券】處置期間: 1150630~1150713 。現正執行人工管制撮合及預收款券等處置措施。",
        "IsDisposed":  true,
        "DisposedPeriod":  "1150630~1150713",
        "Calculations":  [

                         ],
        "VolumeCalculations":  [

                               ]
    },
    {
        "Code":  "2061",
        "Name":  "風青",
        "Market":  "上櫃",
        "Close":  "58",
        "Reason":  "【已處置有價證券】處置期間: 1150624~1150707 。現正執行人工管制撮合及預收款券等處置措施。",
        "IsDisposed":  true,
        "DisposedPeriod":  "1150624~1150707",
        "Calculations":  [

                         ],
        "VolumeCalculations":  [

                               ]
    },
    {
        "Code":  "24553",
        "Name":  "全新三",
        "Market":  "上櫃",
        "Close":  "N/A",
        "Reason":  "【已處置有價證券】處置期間: 1150622~1150703 。現正執行人工管制撮合及預收款券等處置措施。",
        "IsDisposed":  true,
        "DisposedPeriod":  "1150622~1150703",
        "Calculations":  [

                         ],
        "VolumeCalculations":  [

                               ]
    },
    {
        "Code":  "49231",
        "Name":  "力士一",
        "Market":  "上櫃",
        "Close":  "N/A",
        "Reason":  "【已處置有價證券】處置期間: 1150624~1150707 。現正執行人工管制撮合及預收款券等處置措施。",
        "IsDisposed":  true,
        "DisposedPeriod":  "1150624~1150707",
        "Calculations":  [

                         ],
        "VolumeCalculations":  [

                               ]
    },
    {
        "Code":  "7712",
        "Name":  "博盛半導體",
        "Market":  "上櫃",
        "Close":  "202.5",
        "Reason":  "【已處置有價證券】處置期間: 1150625~1150708 。現正執行人工管制撮合及預收款券等處置措施。",
        "IsDisposed":  true,
        "DisposedPeriod":  "1150625~1150708",
        "Calculations":  [

                         ],
        "VolumeCalculations":  [

                               ]
    },
    {
        "Code":  "2481",
        "Name":  "強茂",
        "Market":  "上市",
        "Close":  "192",
        "Reason":  "【已處置有價證券】處置期間: 115/06/26～115/07/09 。現正執行人工管制撮合及預收款券等處置措施。",
        "IsDisposed":  true,
        "DisposedPeriod":  "115/06/26～115/07/09",
        "Calculations":  [

                         ],
        "VolumeCalculations":  [

                               ]
    },
    {
        "Code":  "7610",
        "Name":  "聯友金屬-創",
        "Market":  "上市",
        "Close":  "2505",
        "Reason":  "【已處置有價證券】處置期間: 115/06/24～115/07/07 。現正執行人工管制撮合及預收款券等處置措施。",
        "IsDisposed":  true,
        "DisposedPeriod":  "115/06/24～115/07/07",
        "Calculations":  [

                         ],
        "VolumeCalculations":  [

                               ]
    },
    {
        "Code":  "8024",
        "Name":  "佑華",
        "Market":  "上櫃",
        "Close":  "17.450000762939453",
        "Reason":  "【已處置有價證券】處置期間: 1150630~1150713 。現正執行人工管制撮合及預收款券等處置措施。",
        "IsDisposed":  true,
        "DisposedPeriod":  "1150630~1150713",
        "Calculations":  [

                         ],
        "VolumeCalculations":  [

                               ]
    },
    {
        "Code":  "72657U",
        "Name":  "家登群益56售04",
        "Market":  "上櫃",
        "Close":  "23",
        "Reason":  "【已處置有價證券】處置期間: 1150623~1150706 。現正執行人工管制撮合及預收款券等處置措施。",
        "IsDisposed":  true,
        "DisposedPeriod":  "1150623~1150706",
        "Calculations":  [

                         ],
        "VolumeCalculations":  [

                               ]
    },
    {
        "Code":  "1617",
        "Name":  "榮星",
        "Market":  "上市",
        "Close":  "24.50",
        "Reason":  "【已處置有價證券】處置期間: 115/07/06～115/07/17 。現正執行人工管制撮合及預收款券等處置措施。",
        "IsDisposed":  true,
        "DisposedPeriod":  "115/07/06～115/07/17",
        "Calculations":  [

                         ],
        "VolumeCalculations":  [

                               ]
    },
    {
        "Code":  "5425",
        "Name":  "台半",
        "Market":  "上櫃",
        "Close":  "130",
        "Reason":  "【已處置有價證券】處置期間: 1150626~1150709 。現正執行人工管制撮合及預收款券等處置措施。",
        "IsDisposed":  true,
        "DisposedPeriod":  "1150626~1150709",
        "Calculations":  [

                         ],
        "VolumeCalculations":  [

                               ]
    },
    {
        "Code":  "6488",
        "Name":  "環球晶",
        "Market":  "上櫃",
        "Close":  "950",
        "Reason":  "【已處置有價證券】處置期間: 1150622~1150703 。現正執行人工管制撮合及預收款券等處置措施。",
        "IsDisposed":  true,
        "DisposedPeriod":  "1150622~1150703",
        "Calculations":  [

                         ],
        "VolumeCalculations":  [

                               ]
    },
    {
        "Code":  "6683",
        "Name":  "雍智科技",
        "Market":  "上櫃",
        "Close":  "1885",
        "Reason":  "【已處置有價證券】處置期間: 1150629~1150710 。現正執行人工管制撮合及預收款券等處置措施。",
        "IsDisposed":  true,
        "DisposedPeriod":  "1150629~1150710",
        "Calculations":  [

                         ],
        "VolumeCalculations":  [

                               ]
    },
    {
        "Code":  "911608",
        "Name":  "明輝-DR",
        "Market":  "上市",
        "Close":  "2.85",
        "Reason":  "【已處置有價證券】處置期間: 115/07/06～115/07/17 。現正執行人工管制撮合及預收款券等處置措施。",
        "IsDisposed":  true,
        "DisposedPeriod":  "115/07/06～115/07/17",
        "Calculations":  [

                         ],
        "VolumeCalculations":  [

                               ]
    },
    {
        "Code":  "2303",
        "Name":  "聯電",
        "Market":  "上市",
        "Close":  "169",
        "Reason":  "【已處置有價證券】處置期間: 115/07/02～115/07/15 。現正執行人工管制撮合及預收款券等處置措施。",
        "IsDisposed":  true,
        "DisposedPeriod":  "115/07/02～115/07/15",
        "Calculations":  [

                         ],
        "VolumeCalculations":  [

                               ]
    },
    {
        "Code":  "3055",
        "Name":  "蔚華科",
        "Market":  "上市",
        "Close":  "152.50",
        "Reason":  "【已處置有價證券】處置期間: 115/07/06～115/07/17 。現正執行人工管制撮合及預收款券等處置措施。",
        "IsDisposed":  true,
        "DisposedPeriod":  "115/07/06～115/07/17",
        "Calculations":  [

                         ],
        "VolumeCalculations":  [

                               ]
    },
    {
        "Code":  "5468",
        "Name":  "凱鈺",
        "Market":  "上櫃",
        "Close":  "23.899999618530273",
        "Reason":  "【已處置有價證券】處置期間: 1150624~1150707 。現正執行人工管制撮合及預收款券等處置措施。",
        "IsDisposed":  true,
        "DisposedPeriod":  "1150624~1150707",
        "Calculations":  [

                         ],
        "VolumeCalculations":  [

                               ]
    },
    {
        "Code":  "8996",
        "Name":  "高力",
        "Market":  "上市",
        "Close":  "1555",
        "Reason":  "【已處置有價證券】處置期間: 115/06/24～115/07/07 。現正執行人工管制撮合及預收款券等處置措施。",
        "IsDisposed":  true,
        "DisposedPeriod":  "115/06/24～115/07/07",
        "Calculations":  [

                         ],
        "VolumeCalculations":  [

                               ]
    },
    {
        "Code":  "1435",
        "Name":  "中福",
        "Market":  "上市",
        "Close":  "29.75",
        "Reason":  "【已處置有價證券】處置期間: 115/06/30～115/07/13 。現正執行人工管制撮合及預收款券等處置措施。",
        "IsDisposed":  true,
        "DisposedPeriod":  "115/06/30～115/07/13",
        "Calculations":  [

                         ],
        "VolumeCalculations":  [

                               ]
    },
    {
        "Code":  "7795",
        "Name":  "長廣",
        "Market":  "上市",
        "Close":  "626.00",
        "Reason":  "【已處置有價證券】處置期間: 115/07/06～115/07/17 。現正執行人工管制撮合及預收款券等處置措施。",
        "IsDisposed":  true,
        "DisposedPeriod":  "115/07/06～115/07/17",
        "Calculations":  [

                         ],
        "VolumeCalculations":  [

                               ]
    },
    {
        "Code":  "62433",
        "Name":  "迅杰三",
        "Market":  "上櫃",
        "Close":  "N/A",
        "Reason":  "【已處置有價證券】處置期間: 1150629~1150710 。現正執行人工管制撮合及預收款券等處置措施。",
        "IsDisposed":  true,
        "DisposedPeriod":  "1150629~1150710",
        "Calculations":  [

                         ],
        "VolumeCalculations":  [

                               ]
    },
    {
        "Code":  "4764",
        "Name":  "雙鍵",
        "Market":  "上市",
        "Close":  "332",
        "Reason":  "【已處置有價證券】處置期間: 115/06/24～115/07/07 。現正執行人工管制撮合及預收款券等處置措施。",
        "IsDisposed":  true,
        "DisposedPeriod":  "115/06/24～115/07/07",
        "Calculations":  [

                         ],
        "VolumeCalculations":  [

                               ]
    },
    {
        "Code":  "5321",
        "Name":  "美而快",
        "Market":  "上櫃",
        "Close":  "45.54999923706055",
        "Reason":  "【已處置有價證券】處置期間: 1150629~1150710 。現正執行人工管制撮合及預收款券等處置措施。",
        "IsDisposed":  true,
        "DisposedPeriod":  "1150629~1150710",
        "Calculations":  [

                         ],
        "VolumeCalculations":  [

                               ]
    },
    {
        "Code":  "085788",
        "Name":  "T50反1中信5C購01",
        "Market":  "上市",
        "Close":  "1.6299999952316284",
        "Reason":  "【已處置有價證券】處置期間: 115/06/29～115/07/10 。現正執行人工管制撮合及預收款券等處置措施。",
        "IsDisposed":  true,
        "DisposedPeriod":  "115/06/29～115/07/10",
        "Calculations":  [

                         ],
        "VolumeCalculations":  [

                               ]
    },
    {
        "Code":  "1447",
        "Name":  "力鵬",
        "Market":  "上市",
        "Close":  "9.99",
        "Reason":  "【已處置有價證券】處置期間: 115/07/06～115/07/17 。現正執行人工管制撮合及預收款券等處置措施。",
        "IsDisposed":  true,
        "DisposedPeriod":  "115/07/06～115/07/17",
        "Calculations":  [

                         ],
        "VolumeCalculations":  [

                               ]
    },
    {
        "Code":  "3675",
        "Name":  "德微",
        "Market":  "上櫃",
        "Close":  "405",
        "Reason":  "【已處置有價證券】處置期間: 1150625~1150708 。現正執行人工管制撮合及預收款券等處置措施。",
        "IsDisposed":  true,
        "DisposedPeriod":  "1150625~1150708",
        "Calculations":  [

                         ],
        "VolumeCalculations":  [

                               ]
    },
    {
        "Code":  "3450",
        "Name":  "聯鈞",
        "Market":  "上市",
        "Close":  "505",
        "Reason":  "【已處置有價證券】處置期間: 115/06/30～115/07/13 。現正執行人工管制撮合及預收款券等處置措施。",
        "IsDisposed":  true,
        "DisposedPeriod":  "115/06/30～115/07/13",
        "Calculations":  [

                         ],
        "VolumeCalculations":  [

                               ]
    },
    {
        "Code":  "6141",
        "Name":  "柏承",
        "Market":  "上市",
        "Close":  "42.299999237060547",
        "Reason":  "【已處置有價證券】處置期間: 115/06/26～115/07/09 。現正執行人工管制撮合及預收款券等處置措施。",
        "IsDisposed":  true,
        "DisposedPeriod":  "115/06/26～115/07/09",
        "Calculations":  [

                         ],
        "VolumeCalculations":  [

                               ]
    },
    {
        "Code":  "5489",
        "Name":  "彩富",
        "Market":  "上櫃",
        "Close":  "61.900001525878906",
        "Reason":  "【已處置有價證券】處置期間: 1150626~1150709 。現正執行人工管制撮合及預收款券等處置措施。",
        "IsDisposed":  true,
        "DisposedPeriod":  "1150626~1150709",
        "Calculations":  [

                         ],
        "VolumeCalculations":  [

                               ]
    },
    {
        "Code":  "6834",
        "Name":  "天二科技",
        "Market":  "上市",
        "Close":  "125.5",
        "Reason":  "【已處置有價證券】處置期間: 115/06/26～115/07/09 。現正執行人工管制撮合及預收款券等處置措施。",
        "IsDisposed":  true,
        "DisposedPeriod":  "115/06/26～115/07/09",
        "Calculations":  [

                         ],
        "VolumeCalculations":  [

                               ]
    },
    {
        "Code":  "6693",
        "Name":  "廣閎科",
        "Market":  "上櫃",
        "Close":  "236.5",
        "Reason":  "【已處置有價證券】處置期間: 1150624~1150707 。現正執行人工管制撮合及預收款券等處置措施。",
        "IsDisposed":  true,
        "DisposedPeriod":  "1150624~1150707",
        "Calculations":  [

                         ],
        "VolumeCalculations":  [

                               ]
    }
]
